[{"keywords": "NAME:(AI OR ML)", "count": 54, "requirements": [{"name": "of", "count": 10, "persent": 8}, {"name": "management", "count": 8, "persent": 6}, {"name": "product", "count": 5, "persent": 4}, {"name": "a", "count": 5, "persent": 4}, {"name": "and", "count": 5, "persent": 4}, {"name": "software", "count": 5, "persent": 4}, {"name": "python", "count": 4, "persent": 3}, {"name": "minimum", "count": 4, "persent": 3}, {"name": "years", "count": 4, "persent": 3}, {"name": "experience", "count": 4, "persent": 3}, {"name": "in", "count": 4, "persent": 3}, {"name": "or", "count": 4, "persent": 3}, {"name": "engineering", "count": 4, "persent": 3}, {"name": "prior", "count": 4, "persent": 3}, {"name": "development", "count": 4, "persent": 3}, {"name": "cycle", "count": 4, "persent": 3}, {"name": "is", "count": 4, "persent": 3}, {"name": "must", "count": 4, "persent": 3}, {"name": "kubernetes", "count": 3, "persent": 2}, {"name": "osi", "count": 2, "persent": 2}, {"name": "tcp", "count": 2, "persent": 2}, {"name": "ip", "count": 2, "persent": 2}, {"name": "unix", "count": 2, "persent": 2}, {"name": "manager", "count": 2, "persent": 2}, {"name": "middle", "count": 2, "persent": 2}, {"name": "developer", "count": 2, "persent": 2}, {"name": "ai", "count": 2, "persent": 2}, {"name": "data", "count": 2, "persent": 2}, {"name": "project", "count": 1, "persent": 1}, {"name": "cv", "count": 1, "persent": 1}, {"name": "ml", "count": 1, "persent": 1}, {"name": "ios", "count": 1, "persent": 1}, {"name": "android", "count": 1, "persent": 1}, {"name": "you", "count": 1, "persent": 1}, {"name": "should", "count": 1, "persent": 1}, {"name": "also", "count": 1, "persent": 1}, {"name": "have", "count": 1, "persent": 1}, {"name": "strong", "count": 1, "persent": 1}, {"name": "understanding", "count": 1, "persent": 1}, {"name": "structures", "count": 1, "persent": 1}, {"name": "modeling", "count": 1, "persent": 1}, {"name": "architecture", "count": 1, "persent": 1}, {"name": "deep", "count": 1, "persent": 1}, {"name": "knowledge", "count": 1, "persent": 1}, {"name": "math", "count": 1, "persent": 1}, {"name": "probability", "count": 1, "persent": 1}, {"name": "mlops", "count": 1, "persent": 1}, {"name": "devops", "count": 1, "persent": 1}, {"name": "pytorch", "count": 1, "persent": 1}, {"name": "pytorchlightning", "count": 1, "persent": 1}, {"name": "pandas", "count": 1, "persent": 1}, {"name": "numpy", "count": 1, "persent": 1}, {"name": "sql", "count": 1, "persent": 1}, {"name": "stem", "count": 1, "persent": 1}]}]